python_size-0.1.1.dist-info/DESCRIPTION.rst
python_size-0.1.1.dist-info/METADATA
python_size-0.1.1.dist-info/RECORD
python_size-0.1.1.dist-info/WHEEL
python_size-0.1.1.dist-info/metadata.json
python_size-0.1.1.dist-info/pbr.json
python_size-0.1.1.dist-info/top_level.txt
size/__init__.py
size/size.py
