Metadata-Version: 2.1
Name: python-size
Version: 0.1.1
Summary: Size converter that supports both SI and IEC standards.
Home-page: UNKNOWN
Author: Jared Rodriguez
Author-email: jared@blacknode.net
License: Apache-2.0
Platform: UNKNOWN
